music_link_conv/__init__.py
music_link_conv/aliases.py
music_link_conv/api.py
music_link_conv/py.typed
music_link_conv-0.0.1b4.dist-info/METADATA
music_link_conv-0.0.1b4.dist-info/WHEEL
music_link_conv-0.0.1b4.dist-info/RECORD
