Metadata-Version: 2.4
Name: music-link-conv
Version: 0.0.1b4
Summary: Library for converting platform link x to platform link y
Author: An0nimia
Author-email: an0nimia@protonmail.com
Requires-Python: >=3.12,<4.0
Classifier: Programming Language :: Python :: 3
Classifier: Programming Language :: Python :: 3.12
Classifier: Programming Language :: Python :: 3.13
Classifier: Programming Language :: Python :: 3.14
Requires-Dist: api-deezer (>=0.0.1b7,<0.0.2)
Requires-Dist: api-spotify (>=0.0.1b7,<0.0.2)
Requires-Dist: pydantic (>=2.11.7,<3.0.0)
Requires-Dist: requests (>=2.32.4,<3.0.0)
